{
  "id": "pgps9k_152",
  "meta": [
    {
      "label": "PGPS9K"
    },
    {
      "label": "#152"
    },
    {
      "label": "3-turn · 2 rejects + retry",
      "tag": true
    }
  ],
  "question": "PRYZ is a rhombus. If RK = 5, RY = 13 and m \\angle YRZ = 67, what is m \\angle PKR?",
  "choices": [
    {
      "key": "A",
      "value": "23"
    },
    {
      "key": "B",
      "value": "46"
    },
    {
      "key": "C",
      "value": "90"
    },
    {
      "key": "D",
      "value": "134"
    }
  ],
  "expected": "C",
  "input_image": "assets/demos/pgps9k_152_input.png",
  "viewport": [
    -15.0,
    15.0,
    -3.0,
    27.0
  ],
  "turns": [
    {
      "index": 1,
      "phase": null,
      "signal": null,
      "summary": "5 ok · 6 ✗",
      "steps": [
        {
          "raw": {
            "tool": "add_point",
            "args": {
              "name": "R",
              "x": 0,
              "y": 0
            }
          },
          "cmd": "R = (0, 0)",
          "ok": true,
          "diff": [
            [
              "R",
              "point",
              "R = (0, 0)"
            ]
          ],
          "note": ""
        },
        {
          "raw": {
            "tool": "add_point",
            "args": {
              "name": "K",
              "x": 5,
              "y": 0
            }
          },
          "cmd": "K = (5, 0)",
          "ok": true,
          "diff": [
            [
              "K",
              "point",
              "K = (5, 0)"
            ]
          ],
          "note": ""
        },
        {
          "raw": {
            "tool": "add_point",
            "args": {
              "name": "Z",
              "x": 10,
              "y": 0
            }
          },
          "cmd": "Z = (10, 0)",
          "ok": true,
          "diff": [
            [
              "Z",
              "point",
              "Z = (10, 0)"
            ]
          ],
          "note": ""
        },
        {
          "raw": {
            "tool": "add_perpendicular_line",
            "args": {
              "name": "perp_K",
              "point": "K",
              "line": "line_RZ"
            }
          },
          "cmd": "perp_K = PerpendicularLine(K, line_RZ)",
          "ok": false,
          "diff": [],
          "note": ""
        },
        {
          "raw": {
            "tool": "add_line",
            "args": {
              "name": "line_RZ",
              "p1": "R",
              "p2": "Z"
            }
          },
          "cmd": "line_RZ = Line(R, Z)",
          "ok": true,
          "diff": [
            [
              "line_RZ",
              "line",
              "line_RZ: y = 0"
            ]
          ],
          "note": ""
        },
        {
          "raw": {
            "tool": "add_circle",
            "args": {
              "name": "circ_R13",
              "center": "R",
              "radius": 13
            }
          },
          "cmd": "circ_R13 = Circle(R, 13)",
          "ok": true,
          "diff": [
            [
              "circ_R13",
              "circle",
              "circ_R13: x² + y² = 169"
            ]
          ],
          "note": ""
        },
        {
          "raw": {
            "tool": "add_intersect",
            "args": {
              "name": "Y",
              "obj1": "perp_K",
              "obj2": "circ_R13",
              "index": 1
            }
          },
          "cmd": "Y = Intersect(perp_K, circ_R13, 1)",
          "ok": false,
          "diff": [],
          "note": ""
        },
        {
          "raw": {
            "tool": "add_intersect",
            "args": {
              "name": "P_temp",
              "obj1": "perp_K",
              "obj2": "circ_R13",
              "index": 2
            }
          },
          "cmd": "P_temp = Intersect(perp_K, circ_R13, 2)",
          "ok": false,
          "diff": [],
          "note": ""
        },
        {
          "raw": {
            "tool": "rename_object",
            "args": {
              "name": "P_temp",
              "new_name": "P"
            }
          },
          "cmd": "Rename(P_temp→P)",
          "ok": false,
          "diff": [],
          "note": "Object 'P_temp' does not exist"
        },
        {
          "raw": {
            "tool": "add_polygon",
            "args": {
              "name": "rhombus_PRYZ",
              "points": "P,R,Y,Z"
            }
          },
          "cmd": "rhombus_PRYZ = Polygon(P, R, Y, Z)",
          "ok": false,
          "diff": [],
          "note": ""
        },
        {
          "raw": {
            "tool": "query_angle",
            "args": {
              "name": "angle_PKR",
              "a": "P",
              "b": "K",
              "c": "R"
            }
          },
          "cmd": "angle_PKR = Angle(P, K, R)",
          "ok": false,
          "diff": [],
          "note": ""
        }
      ]
    },
    {
      "index": 2,
      "phase": null,
      "signal": null,
      "summary": "6 ok",
      "steps": [
        {
          "raw": {
            "tool": "add_line",
            "args": {
              "name": "line_RZ",
              "p1": "R",
              "p2": "Z"
            }
          },
          "cmd": "line_RZ = Line(R, Z)",
          "ok": true,
          "diff": [],
          "note": ""
        },
        {
          "raw": {
            "tool": "add_perpendicular_line",
            "args": {
              "name": "perp_K",
              "point": "K",
              "line": "line_RZ"
            }
          },
          "cmd": "perp_K = PerpendicularLine(K, line_RZ)",
          "ok": true,
          "diff": [
            [
              "perp_K",
              "line",
              "perp_K: x = 5"
            ]
          ],
          "note": ""
        },
        {
          "raw": {
            "tool": "add_intersect",
            "args": {
              "name": "Y",
              "obj1": "perp_K",
              "obj2": "circ_R13",
              "index": 1
            }
          },
          "cmd": "Y = Intersect(perp_K, circ_R13, 1)",
          "ok": true,
          "diff": [
            [
              "Y",
              "point",
              "Y = (5, -12)"
            ]
          ],
          "note": ""
        },
        {
          "raw": {
            "tool": "add_intersect",
            "args": {
              "name": "P_temp",
              "obj1": "perp_K",
              "obj2": "circ_R13",
              "index": 2
            }
          },
          "cmd": "P_temp = Intersect(perp_K, circ_R13, 2)",
          "ok": true,
          "diff": [
            [
              "P_temp",
              "point",
              "P_temp = (5, 12)"
            ]
          ],
          "note": ""
        },
        {
          "raw": {
            "tool": "rename_object",
            "args": {
              "name": "P_temp",
              "new_name": "P"
            }
          },
          "cmd": "Rename(P_temp→P)",
          "ok": true,
          "diff": [
            [
              "P_temp",
              "renamed",
              "→ P"
            ],
            [
              "P",
              "object",
              "P (renamed from P_temp)"
            ]
          ],
          "note": ""
        },
        {
          "raw": {
            "tool": "query_angle",
            "args": {
              "name": "angle_PKR",
              "a": "P",
              "b": "K",
              "c": "R"
            }
          },
          "cmd": "angle_PKR = Angle(P, K, R)",
          "ok": true,
          "diff": [
            [
              "angle_PKR",
              "numeric",
              "angle_PKR = 90.0"
            ]
          ],
          "note": ""
        }
      ]
    },
    {
      "index": 3,
      "phase": null,
      "signal": "answer_emit",
      "summary": "0 ok",
      "steps": []
    }
  ],
  "answer": {
    "value": "C",
    "choice": "C"
  }
}